kaiten/KaitenClient.py
kaiten/__init__.py
kaiten/kaiten.py
kaiten/resources/Board.py
kaiten/resources/Card.py
kaiten/resources/ListOf.py
kaiten/resources/Property.py
kaiten/resources/Resource.py
kaiten/resources/Space.py
kaiten/resources/Tag.py
kaiten/resources/User.py
kaiten/resources/__init__.py
kaiten/resources/test.py
kaiten-1.0.0.dist-info/LICENSE
kaiten-1.0.0.dist-info/METADATA
kaiten-1.0.0.dist-info/WHEEL
kaiten-1.0.0.dist-info/top_level.txt
kaiten-1.0.0.dist-info/RECORD
