Metadata-Version: 2.1
Name: kaiten
Version: 1.0.0
Summary: Python Kaiten API client for convenient work with it
Home-page: https://github.com/Xitroy/Kaiten/
Author: Xitroy
Author-email: ymh9w@yandex.ru
Classifier: Programming Language :: Python :: 3.9
Classifier: License :: OSI Approved :: GNU General Public License v3 (GPLv3)
License-File: LICENSE
Requires-Dist: requests (>=2)
